sphinx_prime_applets/__init__.py
sphinx_prime_applets/_version.py
sphinx_prime_applets-1.2.5.dist-info/METADATA
sphinx_prime_applets-1.2.5.dist-info/WHEEL
sphinx_prime_applets-1.2.5.dist-info/licenses/LICENSE
sphinx_prime_applets-1.2.5.dist-info/RECORD
