Metadata-Version: 2.4
Name: sphinx-prime-applets
Version: 1.2.5
Summary: A custom Sphinx extension to easily embed PRIME applets in a Sphinx book
Author-email: PRIME <PRIME@tudelft.nl>
License: MIT License
License-File: LICENSE
Requires-Python: >=3.10
Requires-Dist: sphinx
Requires-Dist: sphinx-metadata-figure>=1.0.3
